CHANGES.rst
COPYING
LICENSE
MANIFEST.in
README.rst
setup.py
Manager.egg-info/PKG-INFO
Manager.egg-info/SOURCES.txt
Manager.egg-info/dependency_links.txt
Manager.egg-info/requires.txt
Manager.egg-info/top_level.txt
docs/help/Manager_Manual.html
docs/help/Manager_Manual.rst
docs/sphinx/Makefile
docs/sphinx/build/doctrees/environment.pickle
docs/sphinx/build/doctrees/index.doctree
docs/sphinx/build/doctrees/resources/pages/about.doctree
docs/sphinx/build/doctrees/resources/pages/api.doctree
docs/sphinx/build/doctrees/resources/pages/changes.doctree
docs/sphinx/build/doctrees/resources/pages/installation.doctree
docs/sphinx/build/doctrees/resources/pages/introduction.doctree
docs/sphinx/build/doctrees/resources/pages/usage.doctree
docs/sphinx/build/doctrees/resources/pages/api/manager.component.doctree
docs/sphinx/build/doctrees/resources/pages/api/manager.componentsManager.doctree
docs/sphinx/build/doctrees/resources/pages/api/manager.exceptions.doctree
docs/sphinx/build/doctrees/resources/pages/api/manager.globals.constants.doctree
docs/sphinx/build/doctrees/resources/pages/api/manager.qobjectComponent.doctree
docs/sphinx/build/doctrees/resources/pages/api/manager.qwidgetComponent.doctree
docs/sphinx/build/html/.buildinfo
docs/sphinx/build/html/genindex.html
docs/sphinx/build/html/index.html
docs/sphinx/build/html/objects.inv
docs/sphinx/build/html/py-modindex.html
docs/sphinx/build/html/search.html
docs/sphinx/build/html/searchindex.js
docs/sphinx/build/html/_modules/index.html
docs/sphinx/build/html/_modules/manager/component.html
docs/sphinx/build/html/_modules/manager/componentsManager.html
docs/sphinx/build/html/_modules/manager/exceptions.html
docs/sphinx/build/html/_modules/manager/qobjectComponent.html
docs/sphinx/build/html/_modules/manager/qwidgetComponent.html
docs/sphinx/build/html/_modules/manager/globals/constants.html
docs/sphinx/build/html/_sources/index.txt
docs/sphinx/build/html/_sources/resources/pages/about.txt
docs/sphinx/build/html/_sources/resources/pages/api.txt
docs/sphinx/build/html/_sources/resources/pages/changes.txt
docs/sphinx/build/html/_sources/resources/pages/installation.txt
