Metadata-Version: 1.1
Name: Manager
Version: 2.0.5
Summary: Manager is the Components Manager package of Umbra, sIBL_GUI and sIBL_Reporter.
Home-page: https://github.com/KelSolaar/Manager
Author: Thomas Mansencal
Author-email: thomas.mansencal@gmail.com
License: GPLv3
Platform: UNKNOWN
Classifier: Development Status :: 5 - Production/Stable
Classifier: Environment :: Console
Classifier: Intended Audience :: Developers
Classifier: License :: OSI Approved :: GNU General Public License v3 (GPLv3)
Classifier: Natural Language :: English
Classifier: Operating System :: OS Independent
Classifier: Programming Language :: Python :: 2.7
Classifier: Topic :: Utilities
